{
  "project_info": {
    "project_number": "833034953489",
    "project_id": "mymeet-cd1eb",
    "storage_bucket": "mymeet-cd1eb.firebasestorage.app"
  },
  "client": [
    {
      "client_info": {
        "mobilesdk_app_id": "1:833034953489:android:e15ef5c38c1765b4f0a2b0",
        "android_client_info": {
          "package_name": "com.example.my_meet"
        }
      },
      "oauth_client": [],
      "api_key": [
        {
          "current_key": "AIzaSyCFBbh_gocuatuUizUjJeVZ3MkpYj-mtBA"
        }
      ],
      "services": {
        "appinvite_service": {
          "other_platform_oauth_client": []
        }
      }
    }
  ],
  "configuration_version": "1"
}